LICENSE.md
MANIFEST.in
README.md
dynamic_extras_require.txt
dynamic_install_requires.txt
quicklib_incorporated.v2.5.zip
quicklib_setup_from_yml.py
epic/jupyter/__init__.py
epic/jupyter/__version__.py
epic/jupyter/_utils.py
epic/jupyter/display.py
epic/jupyter/initialization.py
epic/jupyter/interpolate.py
epic/jupyter/ipython.py
epic/jupyter/nbcode.py
epic/jupyter/tests/__init__.py
epic/jupyter/tests/helpers.py
epic/jupyter/tests/test_display.py
epic/jupyter/tests/test_initialization.py
epic/jupyter/tests/test_ipython.py
epic/jupyter/tests/test_magic.py
epic/jupyter/tests/test_nbcode.py
epic_jupyter.egg-info/PKG-INFO
epic_jupyter.egg-info/SOURCES.txt
epic_jupyter.egg-info/dependency_links.txt
epic_jupyter.egg-info/top_level.txt